setup.py
reverse_ws/__init__.py
reverse_ws/websocket_handler.py
reverse_ws.egg-info/PKG-INFO
reverse_ws.egg-info/SOURCES.txt
reverse_ws.egg-info/dependency_links.txt
reverse_ws.egg-info/requires.txt
reverse_ws.egg-info/top_level.txt