Metadata-Version: 2.1
Name: reverse_ws
Version: 0.1
Requires-Dist: websockets
